py.typed
honeyhive/__init__.py
honeyhive/_hooks/__init__.py
honeyhive/_hooks/sdkhooks.py
honeyhive/_hooks/types.py
honeyhive/basesdk.py
honeyhive/cli/__init__.py
honeyhive/cli/__main__.py
honeyhive/cli/eval.py
honeyhive/configurations.py
honeyhive/datapoints.py
honeyhive/datasets.py
honeyhive/evaluation/__init__.py
honeyhive/evaluation/evaluators.py
honeyhive/events.py
honeyhive/experiments.py
honeyhive/httpclient.py
honeyhive/metrics.py
honeyhive/models/components/__init__.py
honeyhive/models/components/configuration.py
honeyhive/models/components/createdatapointrequest.py
honeyhive/models/components/createdatasetrequest.py
honeyhive/models/components/createeventrequest.py
honeyhive/models/components/createmodelevent.py
honeyhive/models/components/createprojectrequest.py
honeyhive/models/components/createrunrequest.py
honeyhive/models/components/createrunresponse.py
honeyhive/models/components/createtoolrequest.py
honeyhive/models/components/datapoint.py
honeyhive/models/components/dataset.py
honeyhive/models/components/datasetupdate.py
honeyhive/models/components/deleterunresponse.py
honeyhive/models/components/evaluationrun.py
honeyhive/models/components/event.py
honeyhive/models/components/eventfilter.py
honeyhive/models/components/experimentcomparisonresponse.py
honeyhive/models/components/experimentresultresponse.py
honeyhive/models/components/getrunresponse.py
honeyhive/models/components/getrunsresponse.py
honeyhive/models/components/metric.py
honeyhive/models/components/metricedit.py
honeyhive/models/components/postconfigurationrequest.py
honeyhive/models/components/project.py
honeyhive/models/components/putconfigurationrequest.py
honeyhive/models/components/security.py
honeyhive/models/components/sessionpropertiesbatch.py
honeyhive/models/components/sessionstartrequest.py
honeyhive/models/components/tool.py
honeyhive/models/components/updatedatapointrequest.py
honeyhive/models/components/updateprojectrequest.py
honeyhive-0.2.57.dist-info/LICENSE.md
honeyhive-0.2.57.dist-info/METADATA
honeyhive-0.2.57.dist-info/WHEEL
honeyhive-0.2.57.dist-info/entry_points.txt
honeyhive-0.2.57.dist-info/RECORD
