Metadata-Version: 2.1
Name: HoneyHive
Version: 0.2.57
Summary: The HoneyHive SDK for Python
Home-page: https://github.com/honeyhiveai/python-sdk.git
License: Apache-2.0
Author: HoneyHive
Author-email: support@honeyhive.ai
Requires-Python: >=3.10,<4.0
Classifier: Development Status :: 5 - Production/Stable
Classifier: Intended Audience :: Developers
Classifier: License :: OSI Approved :: Apache Software License
Classifier: Natural Language :: English
Classifier: Programming Language :: Python :: 3
Classifier: Programming Language :: Python :: 3.10
Classifier: Programming Language :: Python :: 3.11
Classifier: Programming Language :: Python :: 3.12
Requires-Dist: dataclasses-json (>=0.6.7)
Requires-Dist: eval-type-backport (>=0.2.0)
Requires-Dist: httpx (>=0.27.0)
Requires-Dist: jsonpath-python (>=1.0.6)
Requires-Dist: pydantic (>=2.10.0)
Requires-Dist: python-dateutil (>=2.8.2)
Requires-Dist: pyyaml (>=6.0.1)
Requires-Dist: requests (>=2.25.1)
Requires-Dist: rich (>=13.9.4)
Requires-Dist: traceloop-sdk (==0.42.0)
Requires-Dist: typing-inspect (>=0.9.0)
Requires-Dist: uplink (>=0.1.0)
Project-URL: Documentation, https://docs.honeyhive.ai/
Project-URL: Repository, https://github.com/honeyhiveai/python-sdk.git
